app/bot_start.py
telegram_periodic_msg_bot/__init__.py
telegram_periodic_msg_bot/_version.py
telegram_periodic_msg_bot/periodic_msg_bot.py
telegram_periodic_msg_bot/bot/__init__.py
telegram_periodic_msg_bot/bot/bot_base.py
telegram_periodic_msg_bot/bot/bot_config.py
telegram_periodic_msg_bot/bot/bot_config_types.py
telegram_periodic_msg_bot/bot/bot_handlers_config.py
telegram_periodic_msg_bot/bot/bot_handlers_config_typing.py
telegram_periodic_msg_bot/command/__init__.py
telegram_periodic_msg_bot/command/command_base.py
telegram_periodic_msg_bot/command/command_data.py
telegram_periodic_msg_bot/command/command_dispatcher.py
telegram_periodic_msg_bot/command/commands.py
telegram_periodic_msg_bot/config/__init__.py
telegram_periodic_msg_bot/config/config_file_sections_loader.py
telegram_periodic_msg_bot/config/config_loader_ex.py
telegram_periodic_msg_bot/config/config_object.py
telegram_periodic_msg_bot/config/config_section_loader.py
telegram_periodic_msg_bot/config/config_sections_loader.py
telegram_periodic_msg_bot/config/config_typing.py
telegram_periodic_msg_bot/lang/lang_en.xml
telegram_periodic_msg_bot/logger/__init__.py
telegram_periodic_msg_bot/logger/logger.py
telegram_periodic_msg_bot/message/__init__.py
telegram_periodic_msg_bot/message/message_deleter.py
telegram_periodic_msg_bot/message/message_dispatcher.py
telegram_periodic_msg_bot/message/message_sender.py
telegram_periodic_msg_bot/misc/__init__.py
telegram_periodic_msg_bot/misc/chat_members.py
telegram_periodic_msg_bot/misc/helpers.py
telegram_periodic_msg_bot/periodic_msg/__init__.py
telegram_periodic_msg_bot/periodic_msg/periodic_msg_job.py
telegram_periodic_msg_bot/periodic_msg/periodic_msg_parser.py
telegram_periodic_msg_bot/periodic_msg/periodic_msg_scheduler.py
telegram_periodic_msg_bot/periodic_msg/periodic_msg_sender.py
telegram_periodic_msg_bot/translator/__init__.py
telegram_periodic_msg_bot/translator/translation_loader.py
telegram_periodic_msg_bot/utils/__init__.py
telegram_periodic_msg_bot-0.4.0.dist-info/licenses/LICENSE
telegram_periodic_msg_bot-0.4.0.dist-info/METADATA
telegram_periodic_msg_bot-0.4.0.dist-info/WHEEL
telegram_periodic_msg_bot-0.4.0.dist-info/top_level.txt
telegram_periodic_msg_bot-0.4.0.dist-info/RECORD
